CandlestickPatterns/__init__.py
CandlestickPatterns/candlestick.py
CandlestickPatterns/patterns/__init__.py
CandlestickPatterns/patterns/bearish_engulfing.py
CandlestickPatterns/patterns/bearish_harami.py
CandlestickPatterns/patterns/bullish_engulfing.py
CandlestickPatterns/patterns/bullish_harami.py
CandlestickPatterns/patterns/candlestick_finder.py
CandlestickPatterns/patterns/dark_cloud_cover.py
CandlestickPatterns/patterns/doji.py
CandlestickPatterns/patterns/doji_star.py
CandlestickPatterns/patterns/dragonfly_doji.py
CandlestickPatterns/patterns/evening_star.py
CandlestickPatterns/patterns/evening_star_doji.py
CandlestickPatterns/patterns/gravestone_doji.py
CandlestickPatterns/patterns/hammer.py
CandlestickPatterns/patterns/hanging_man.py
CandlestickPatterns/patterns/inverted_hammer.py
CandlestickPatterns/patterns/morning_star.py
CandlestickPatterns/patterns/morning_star_doji.py
CandlestickPatterns/patterns/piercing_pattern.py
CandlestickPatterns/patterns/rain_drop.py
CandlestickPatterns/patterns/rain_drop_doji.py
CandlestickPatterns/patterns/shooting_star.py
CandlestickPatterns/patterns/star.py
candlesticks_nikhil-0.0.2.dist-info/LICENSE
candlesticks_nikhil-0.0.2.dist-info/METADATA
candlesticks_nikhil-0.0.2.dist-info/WHEEL
candlesticks_nikhil-0.0.2.dist-info/top_level.txt
candlesticks_nikhil-0.0.2.dist-info/RECORD
